{
  "id": "yucca",
  "type": "tree",
  "display": "Yucca",
  "base_growth_speed": 0.005,
  "base_growth_pow": 0.4,
  "size_scalar": 10,
  "attributes": [
    {
      "name": "water",
      "min": 10,
      "max": 45,
      "base": 45,
      "tolerance": 5000,
      "decay": 0.0015
    },
    {
      "name": "light",
      "base": 100
    },
    {
      "name": "temperature",
      "min": -30,
      "max": 50
    }
  ],
  "textures": [
    {
      "x": 18,
      "y": 0,
      "width": 64,
      "height": 64,
      "base_tint": "#a7da91"
    }
  ]
}